traffic_controller.v
// traffic_controller.v
// Simple 2-way traffic light controller (pure Verilog, synthesizable)

`timescale 1ns/1ps

module traffic_controller #(
    parameter GREEN_CYCLES  = 100,
    parameter YELLOW_CYCLES = 20,
    parameter ALLRED_CYCLES = 10
)(
    input  clk,
    input  rst,                 // synchronous active-high reset
    output reg [2:0] ns_light,  // {R, Y, G}
    output reg [2:0] ew_light   // {R, Y, G}
);

    // State encoding
    parameter S_NS_GREEN  = 3'd0;
    parameter S_NS_YELLOW = 3'd1;
    parameter S_ALL_RED_1 = 3'd2;
    parameter S_EW_GREEN  = 3'd3;
    parameter S_EW_YELLOW = 3'd4;
    parameter S_ALL_RED_2 = 3'd5;

    reg [2:0] state;
    reg [31:0] counter; // 32-bit counter for timing

    // Sequential logic
    always @(posedge clk) begin
        if (rst) begin
            state   <= S_NS_GREEN;
            counter <= 0;
        end else begin
            case (state)
                S_NS_GREEN: begin
                    if (counter >= GREEN_CYCLES - 1) begin
                        state   <= S_NS_YELLOW;
                        counter <= 0;
                    end else counter <= counter + 1;
                end

                S_NS_YELLOW: begin
                    if (counter >= YELLOW_CYCLES - 1) begin
                        state   <= S_ALL_RED_1;
                        counter <= 0;
                    end else counter <= counter + 1;
                end

                S_ALL_RED_1: begin
                    if (counter >= ALLRED_CYCLES - 1) begin
                        state   <= S_EW_GREEN;
                        counter <= 0;
                    end else counter <= counter + 1;
                end

                S_EW_GREEN: begin
                    if (counter >= GREEN_CYCLES - 1) begin
                        state   <= S_EW_YELLOW;
                        counter <= 0;
                    end else counter <= counter + 1;
                end

                S_EW_YELLOW: begin
                    if (counter >= YELLOW_CYCLES - 1) begin
                        state   <= S_ALL_RED_2;
                        counter <= 0;
                    end else counter <= counter + 1;
                end

                S_ALL_RED_2: begin
                    if (counter >= ALLRED_CYCLES - 1) begin
                        state   <= S_NS_GREEN;
                        counter <= 0;
                    end else counter <= counter + 1;
                end

                default: begin
                    state   <= S_NS_GREEN;
                    counter <= 0;
                end
            endcase
        end
    end

    // Combinational logic for light outputs
    always @(*) begin
        ns_light = 3'b100; // default: Red
        ew_light = 3'b100;

        case (state)
            S_NS_GREEN: begin
                ns_light = 3'b001; // Green
                ew_light = 3'b100; // Red
            end
            S_NS_YELLOW: begin
                ns_light = 3'b010; // Yellow
                ew_light = 3'b100; // Red
            end
            S_ALL_RED_1: begin
                ns_light = 3'b100;
                ew_light = 3'b100;
            end
            S_EW_GREEN: begin
                ns_light = 3'b100;
                ew_light = 3'b001;
            end
            S_EW_YELLOW: begin
                ns_light = 3'b100;
                ew_light = 3'b010;
            end
            S_ALL_RED_2: begin
                ns_light = 3'b100;
                ew_light = 3'b100;
            end
        endcase
    end

endmodule

traffic_tb.v
// traffic_tb.v - Testbench for traffic_controller
`timescale 1ns/1ps

module traffic_tb;

    reg clk;
    reg rst;
    wire [2:0] ns_light;
    wire [2:0] ew_light;

    // Instantiate the DUT
    traffic_controller #(
        .GREEN_CYCLES(10),
        .YELLOW_CYCLES(5),
        .ALLRED_CYCLES(3)
    ) uut (
        .clk(clk),
        .rst(rst),
        .ns_light(ns_light),
        .ew_light(ew_light)
    );

    // Clock generation (10ns period)
    always #5 clk = ~clk;

    // Test sequence
    initial begin
        clk = 0;
        rst = 1;
        #20 rst = 0;

        // Run for enough time to complete several cycles
        #500 $finish;
    end

    // Generate waveform
    initial begin
        $dumpfile("traffic_tb.vcd");
        $dumpvars(0, traffic_tb);
    end

    // Display outputs in console
    initial begin
        $display("Time\tNS\tEW");
        $monitor("%0t\t%b\t%b", $time, ns_light, ew_light);
    end

endmodule

traffic_tb.vcd
$date
	Sun Oct 05 09:43:27 2025
$end
$version
	Icarus Verilog
$end
$timescale
	1ps
$end
$scope module traffic_tb $end
$var wire 3 ! ew_light [2:0] $end
$var wire 3 " ns_light [2:0] $end
$var reg 1 # clk $end
$var reg 1 $ rst $end
$scope module uut $end
$var wire 1 % clk $end
$var wire 1 & rst $end
$var reg 32 ' counter [31:0] $end
$var reg 3 ( ew_light [2:0] $end
$var reg 3 ) ns_light [2:0] $end
$var reg 3 * state [2:0] $end
$upscope $end
$upscope $end
$enddefinitions $end
#0
$dumpvars
bx *
bx )
bx (
bx '
1&
0%
1$
0#
bx "
bx !
$end
#5000
b100 (
b100 !
b1 )
b1 "
b0 '
b0 *
1#
1%
#10000
0#
0%
#15000
1#
1%
#20000
0#
0%
0$
0&
#25000
b1 '
1#
1%
#30000
0#
0%
#35000
b10 '
1#
1%
#40000
0#
0%
#45000
b11 '
1#
1%
#50000
0#
0%
#55000
b100 '
1#
1%
#60000
0#
0%
#65000
b101 '
1#
1%
#70000
0#
0%
#75000
b110 '
1#
1%
#80000
0#
0%
#85000
b111 '
1#
1%
#90000
0#
0%
#95000
b1000 '
1#
1%
#100000
0#
0%
#105000
b1001 '
1#
1%
#110000
0#
0%
#115000
b10 )
b10 "
b0 '
b1 *
1#
1%
#120000
0#
0%
#125000
b1 '
1#
1%
#130000
0#
0%
#135000
b10 '
1#
1%
#140000
0#
0%
#145000
b11 '
1#
1%
#150000
0#
0%
#155000
b100 '
1#
1%
#160000
0#
0%
#165000
b100 )
b100 "
b0 '
b10 *
1#
1%
#170000
0#
0%
#175000
b1 '
1#
1%
#180000
0#
0%
#185000
b10 '
1#
1%
#190000
0#
0%
#195000
b1 (
b1 !
b0 '
b11 *
1#
1%
#200000
0#
0%
#205000
b1 '
1#
1%
#210000
0#
0%
#215000
b10 '
1#
1%
#220000
0#
0%
#225000
b11 '
1#
1%
#230000
0#
0%
#235000
b100 '
1#
1%
#240000
0#
0%
#245000
b101 '
1#
1%
#250000
0#
0%
#255000
b110 '
1#
1%
#260000
0#
0%
#265000
b111 '
1#
1%
#270000
0#
0%
#275000
b1000 '
1#
1%
#280000
0#
0%
#285000
b1001 '
1#
1%
#290000
0#
0%
#295000
b10 (
b10 !
b0 '
b100 *
1#
1%
#300000
0#
0%
#305000
b1 '
1#
1%
#310000
0#
0%
#315000
b10 '
1#
1%
#320000
0#
0%
#325000
b11 '
1#
1%
#330000
0#
0%
#335000
b100 '
1#
1%
#340000
0#
0%
#345000
b100 (
b100 !
b0 '
b101 *
1#
1%
#350000
0#
0%
#355000
b1 '
1#
1%
#360000
0#
0%
#365000
b10 '
1#
1%
#370000
0#
0%
#375000
b1 )
b1 "
b0 '
b0 *
1#
1%
#380000
0#
0%
#385000
b1 '
1#
1%
#390000
0#
0%
#395000
b10 '
1#
1%
#400000
0#
0%
#405000
b11 '
1#
1%
#410000
0#
0%
#415000
b100 '
1#
1%
#420000
0#
0%
#425000
b101 '
1#
1%
#430000
0#
0%
#435000
b110 '
1#
1%
#440000
0#
0%
#445000
b111 '
1#
1%
#450000
0#
0%
#455000
b1000 '
1#
1%
#460000
0#
0%
#465000
b1001 '
1#
1%
#470000
0#
0%
#475000
b10 )
b10 "
b0 '
b1 *
1#
1%
#480000
0#
0%
#485000
b1 '
1#
1%
#490000
0#
0%
#495000
b10 '
1#
1%
#500000
0#
0%
#505000
b11 '
1#
1%
#510000
0#
0%
#515000
b100 '
1#
1%
